{
	"credit": "Made with Blockbench",
	"parent": "paro",
	"texture_size": [100, 100],
	"textures": {
		"0": "JoacoEmi/textura pistola 2.0",
		"particle": "JoacoEmi/textura pistola 2.0"
	},
	"elements": [
		{
			"from": [0, 1, 0],
			"to": [1, 3, 10],
			"faces": {
				"north": {"uv": [1.6, 2.88, 1.76, 3.2], "texture": "#0"},
				"east": {"uv": [0, 2.88, 1.6, 3.2], "rotation": 270, "texture": "#0"},
				"south": {"uv": [3.36, 2.88, 3.52, 3.2], "texture": "#0"},
				"west": {"uv": [1.76, 2.88, 3.36, 3.2], "texture": "#0"},
				"up": {"uv": [1.76, 2.88, 1.6, 1.28], "texture": "#0"},
				"down": {"uv": [1.92, 1.28, 1.76, 2.88], "texture": "#0"}
			}
		},
		{
			"from": [3, 1, 0],
			"to": [4, 3, 10],
			"faces": {
				"north": {"uv": [1.6, 2.88, 1.76, 3.2], "texture": "#0"},
				"east": {"uv": [0, 2.88, 1.6, 3.2], "rotation": 270, "texture": "#0"},
				"south": {"uv": [3.36, 2.88, 3.52, 3.2], "texture": "#0"},
				"west": {"uv": [1.76, 2.88, 3.36, 3.2], "texture": "#0"},
				"up": {"uv": [1.76, 2.88, 1.6, 1.28], "texture": "#0"},
				"down": {"uv": [1.92, 1.28, 1.76, 2.88], "texture": "#0"}
			}
		},
		{
			"from": [1, 3, 0],
			"to": [3, 4, 10],
			"faces": {
				"north": {"uv": [1.6, 2.88, 1.92, 3.04], "texture": "#0"},
				"east": {"uv": [0, 2.88, 1.6, 3.04], "rotation": 270, "texture": "#0"},
				"south": {"uv": [3.52, 2.88, 3.84, 3.04], "texture": "#0"},
				"west": {"uv": [1.92, 2.88, 3.52, 3.04], "texture": "#0"},
				"up": {"uv": [1.92, 2.88, 1.6, 1.28], "texture": "#0"},
				"down": {"uv": [2.24, 1.28, 1.92, 2.88], "texture": "#0"}
			}
		},
		{
			"from": [1, 0, 0],
			"to": [3, 1, 10],
			"faces": {
				"north": {"uv": [1.6, 2.88, 1.92, 3.04], "texture": "#0"},
				"east": {"uv": [0, 2.88, 1.6, 3.04], "rotation": 270, "texture": "#0"},
				"south": {"uv": [3.52, 2.88, 3.84, 3.04], "texture": "#0"},
				"west": {"uv": [1.92, 2.88, 3.52, 3.04], "texture": "#0"},
				"up": {"uv": [1.92, 2.88, 1.6, 1.28], "texture": "#0"},
				"down": {"uv": [2.24, 1.28, 1.92, 2.88], "texture": "#0"}
			}
		},
		{
			"from": [0, 0, 10],
			"to": [4, 4, 13],
			"shade": false,
			"faces": {
				"north": {"uv": [5.92, 7.2, 5.28, 7.84], "texture": "#0"},
				"east": {"uv": [6.4, 7.2, 5.92, 7.84], "rotation": 270, "texture": "#0"},
				"south": {"uv": [7.04, 7.2, 6.4, 7.84], "texture": "#0"},
				"west": {"uv": [5.28, 7.2, 4.8, 7.84], "texture": "#0"},
				"up": {"uv": [5.28, 7.2, 5.92, 6.72], "texture": "#0"},
				"down": {"uv": [5.92, 6.72, 6.56, 7.2], "texture": "#0"}
			}
		},
		{
			"from": [0, 0, 13],
			"to": [4, 3, 15],
			"faces": {
				"north": {"uv": [2.4, 5.28, 3.04, 5.76], "texture": "#0"},
				"east": {"uv": [2.08, 5.28, 2.4, 5.76], "rotation": 270, "texture": "#0"},
				"south": {"uv": [3.36, 5.28, 4, 5.76], "texture": "#0"},
				"west": {"uv": [3.04, 5.28, 3.36, 5.76], "texture": "#0"},
				"up": {"uv": [3.04, 5.28, 2.4, 4.96], "texture": "#0"},
				"down": {"uv": [3.68, 4.96, 3.04, 5.28], "texture": "#0"}
			}
		},
		{
			"from": [0, 3, 14],
			"to": [4, 6, 23],
			"rotation": {"angle": 22.5, "axis": "x", "origin": [8, 8, 8]},
			"faces": {
				"north": {"uv": [1.44, 9.76, 2.08, 10.24], "rotation": 270, "texture": "#0"},
				"east": {"uv": [0, 9.76, 1.44, 10.24], "rotation": 270, "texture": "#0"},
				"south": {"uv": [3.52, 9.76, 4.16, 10.24], "rotation": 270, "texture": "#0"},
				"west": {"uv": [2.08, 9.76, 3.52, 10.24], "rotation": 270, "texture": "#0"},
				"up": {"uv": [2.08, 9.76, 1.44, 8.32], "rotation": 270, "texture": "#0"},
				"down": {"uv": [2.72, 8.32, 2.08, 9.76], "rotation": 270, "texture": "#0"}
			}
		},
		{
			"from": [-1, 1, 9],
			"to": [0, 5, 10],
			"rotation": {"angle": -22.5, "axis": "x", "origin": [8, 8, 8]},
			"faces": {
				"north": {"uv": [0.16, 4, 0.32, 4.64], "texture": "#0"},
				"east": {"uv": [0, 4, 0.16, 4.64], "rotation": 270, "texture": "#0"},
				"south": {"uv": [0.48, 4, 0.64, 4.64], "texture": "#0"},
				"west": {"uv": [0.32, 4, 0.48, 4.64], "texture": "#0"},
				"up": {"uv": [0.32, 4, 0.16, 3.84], "texture": "#0"},
				"down": {"uv": [0.48, 3.84, 0.32, 4], "texture": "#0"}
			}
		},
		{
			"from": [4, 1, 9],
			"to": [5, 5, 10],
			"rotation": {"angle": -22.5, "axis": "x", "origin": [8, 8, 8]},
			"faces": {
				"north": {"uv": [0.16, 1.44, 0.32, 2.08], "texture": "#0"},
				"east": {"uv": [0, 1.44, 0.16, 2.08], "rotation": 270, "texture": "#0"},
				"south": {"uv": [0.48, 1.44, 0.64, 2.08], "texture": "#0"},
				"west": {"uv": [0.32, 1.44, 0.48, 2.08], "texture": "#0"},
				"up": {"uv": [0.32, 1.44, 0.16, 1.28], "texture": "#0"},
				"down": {"uv": [0.48, 1.28, 0.32, 1.44], "texture": "#0"}
			}
		},
		{
			"from": [4, 5, 9],
			"to": [5, 6, 11],
			"faces": {
				"north": {"uv": [0.32, 1.76, 0.48, 1.92], "texture": "#0"},
				"east": {"uv": [0, 1.76, 0.32, 1.92], "rotation": 270, "texture": "#0"},
				"south": {"uv": [0.8, 1.76, 0.96, 1.92], "texture": "#0"},
				"west": {"uv": [0.48, 1.76, 0.8, 1.92], "texture": "#0"},
				"up": {"uv": [0.48, 1.76, 0.32, 1.44], "texture": "#0"},
				"down": {"uv": [0.64, 1.44, 0.48, 1.76], "texture": "#0"}
			}
		},
		{
			"from": [-1, 5, 9],
			"to": [0, 6, 11],
			"faces": {
				"north": {"uv": [0.32, 1.76, 0.48, 1.92], "texture": "#0"},
				"east": {"uv": [0, 1.76, 0.32, 1.92], "rotation": 270, "texture": "#0"},
				"south": {"uv": [0.8, 1.76, 0.96, 1.92], "texture": "#0"},
				"west": {"uv": [0.48, 1.76, 0.8, 1.92], "texture": "#0"},
				"up": {"uv": [0.48, 1.76, 0.32, 1.44], "texture": "#0"},
				"down": {"uv": [0.64, 1.44, 0.48, 1.76], "texture": "#0"}
			}
		}
	],
	"display": {
		"thirdperson_righthand": {
			"translation": [2, 3.5, -3.25],
			"scale": [0.39, 0.39, 0.56]
		},
		"thirdperson_lefthand": {
			"translation": [-2.5, 2.5, -4],
			"scale": [0.39, 0.39, 0.53]
		},
		"firstperson_righthand": {
			"translation": [6.5, 6.75, -5],
			"scale": [0.77, 0.82, 0.9]
		},
		"firstperson_lefthand": {
			"translation": [-0.5, 5, -5.75],
			"scale": [0.76, 0.67, 0.87]
		},
		"ground": {
			"translation": [3.5, 1.5, -2.25],
			"scale": [0.52, 0.52, 0.74]
		},
		"gui": {
			"rotation": [20, 130, 17],
			"translation": [-2.5, 5.25, -1.5],
			"scale": [0.62, 0.7, 0.78]
		},
		"head": {
			"rotation": [0, -175, 0],
			"translation": [8.5, -2.75, 6],
			"scale": [0, 0, 0]
		},
		"fixed": {
			"rotation": [0, 90, 0],
			"translation": [-2.25, 5.75, -5.25],
			"scale": [0.99, 0.86, 0.97]
		}
	},
	"groups": [
		{
			"name": "group",
			"origin": [8, 8, 8],
			"children": [0, 1, 2, 3, 4, 5, 6, 7, 8, 9, 10]
		}
	]
}